mlip/__init__.py
mlip/data/__init__.py
mlip/data/chemical_system.py
mlip/data/configs.py
mlip/data/dataset_info.py
mlip/data/graph_dataset_builder.py
mlip/data/chemical_systems_readers/__init__.py
mlip/data/chemical_systems_readers/chemical_systems_reader.py
mlip/data/chemical_systems_readers/combined_reader.py
mlip/data/chemical_systems_readers/extxyz_reader.py
mlip/data/chemical_systems_readers/hdf5_reader.py
mlip/data/chemical_systems_readers/type_aliases.py
mlip/data/chemical_systems_readers/utils.py
mlip/data/helpers/__init__.py
mlip/data/helpers/atomic_energies.py
mlip/data/helpers/atomic_number_table.py
mlip/data/helpers/data_prefetching.py
mlip/data/helpers/data_split.py
mlip/data/helpers/dummy_init_graph.py
mlip/data/helpers/dynamically_batch.py
mlip/data/helpers/edge_vectors.py
mlip/data/helpers/graph_creation.py
mlip/data/helpers/graph_dataset.py
mlip/data/helpers/neighbor_analysis.py
mlip/data/helpers/neighborhood.py
mlip/inference/__init__.py
mlip/inference/batched_inference.py
mlip/models/__init__.py
mlip/models/atomic_energies.py
mlip/models/blocks.py
mlip/models/force_field.py
mlip/models/loss.py
mlip/models/loss_helpers.py
mlip/models/mlip_network.py
mlip/models/model_io.py
mlip/models/options.py
mlip/models/params_loading.py
mlip/models/params_transfer.py
mlip/models/predictor.py
mlip/models/radial_embedding.py
mlip/models/mace/blocks.py
mlip/models/mace/config.py
mlip/models/mace/message_passing.py
mlip/models/mace/models.py
mlip/models/mace/symmetric_contraction.py
mlip/models/nequip/config.py
mlip/models/nequip/models.py
mlip/models/nequip/nequip_helpers.py
mlip/models/visnet/blocks.py
mlip/models/visnet/config.py
mlip/models/visnet/models.py
mlip/simulation/__init__.py
mlip/simulation/enums.py
mlip/simulation/exceptions.py
mlip/simulation/simulation_engine.py
mlip/simulation/state.py
mlip/simulation/temperature_scheduling.py
mlip/simulation/utils.py
mlip/simulation/ase/__init__.py
mlip/simulation/ase/ase_simulation_engine.py
mlip-0.1.8.dist-info/METADATA
mlip-0.1.8.dist-info/WHEEL
mlip-0.1.8.dist-info/licenses/LICENSE
mlip-0.1.8.dist-info/RECORD
