Metadata-Version: 2.4
Name: mlip
Version: 0.1.8
Summary: Machine Learning Interatomic Potentials in JAX
Project-URL: Homepage, https://github.com/instadeepai/mlip/
Author-email: InstaDeep <placeholder@instadeep.com>
License-File: LICENSE
Classifier: Development Status :: 3 - Alpha
Classifier: Environment :: Console
Classifier: Intended Audience :: Developers
Classifier: Intended Audience :: Science/Research
Classifier: License :: OSI Approved :: Apache Software License
Classifier: Operating System :: OS Independent
Classifier: Programming Language :: Python :: 3.11
Classifier: Topic :: Scientific/Engineering :: Artificial Intelligence
Classifier: Topic :: Software Development :: Libraries :: Python Modules
Requires-Python: <3.14,>=3.11
Requires-Dist: ase>=3.22.1
Requires-Dist: dm-haiku>=0.0.14
Requires-Dist: dm-tree>=0.1.8
Requires-Dist: e3nn-jax>=0.20.7
Requires-Dist: flax>=0.9.0
Requires-Dist: h5py>=3.12.1
Requires-Dist: jax-md>=0.2.26
Requires-Dist: jraph
Requires-Dist: matscipy>=1.1.0
Requires-Dist: numpy<3,>1.26.0
Requires-Dist: omegaconf>=2.3.0
Requires-Dist: orbax-checkpoint==0.5.2
Requires-Dist: orbax>=0.1.9
Requires-Dist: pydantic>=2.10.2
Requires-Dist: roundmantissa>=0.2.1
Requires-Dist: tqdm-loggable>=0.2
Requires-Dist: tqdm>=4.0
Provides-Extra: cuda
Requires-Dist: jax[cuda12]>=0.4.32; extra == 'cuda'
Requires-Dist: jaxlib>=0.4.32; extra == 'cuda'
